regex_template/__about__.py
regex_template/__init__.py
regex_template-0.0.1.dist-info/METADATA
regex_template-0.0.1.dist-info/WHEEL
regex_template-0.0.1.dist-info/licenses/LICENSE.txt
regex_template-0.0.1.dist-info/RECORD
