Metadata-Version: 2.4
Name: regex-template
Version: 0.0.1
Summary: Compiled regular expressions with auto-escaped interpolations
Project-URL: Documentation, https://github.com/treyhunner/regex-template#readme
Project-URL: Issues, https://github.com/treyhunner/regex-template/issues
Project-URL: Source, https://github.com/treyhunner/regex-template
Author: Trey Hunner
License-Expression: MIT
License-File: LICENSE.txt
Classifier: Development Status :: 4 - Beta
Classifier: Programming Language :: Python
Classifier: Programming Language :: Python :: 3.14
Classifier: Programming Language :: Python :: Implementation :: CPython
Classifier: Programming Language :: Python :: Implementation :: PyPy
Requires-Python: >=3.14
